{
  "name": "Configuration",
  "base": "PersistedModel",
  "idInjection": true,
  "options": {
    "validateUpsert": true,
    "postgresql": {
      "schema": "public",
      "table": "configuration"
    }
  },
  "properties": {
    "name": {
      "type": "string",
      "required": true,
      "postgresql": {
        "columnName": "name"
      }
    },
    "value": {
      "type": "string",
      "required": true,
      "postgresql": {
        "columnName": "value"
      }
    },
    "entityVersion": {
      "type": "number",
      "postgresql": {
        "columnName": "entity_version"
      }
    }
  },
  "validations": [],
  "relations": {},
  "acls": [],
  "methods": {}
}
